{
  "checksum": ":)",
  "wallpaper": "/home/boing/Pictures/Wallpapers/Wallpapers-Bank/wallpapers/Monocrome-Balls.png",
  "alpha": "100",
  "special": {
    "background": "#dadada",
    "foreground": "#1b1b1b",
    "cursor": "#000000"
  },
  "colors": {
    "color0": "#dadada",
    "color1": "#2e0808",
    "color2": "#714b4b",
    "color3": "#443232",
    "color4": "#000000",
    "color5": "#3b3b3b",
    "color6": "#e8dcdc",
    "color7": "#474747",
    "color8": "#e2e2e2",
    "color9": "#6c5050",
    "color10": "#8f6060",
    "color11": "#614848",
    "color12": "#1a1a1a",
    "color13": "#555555",
    "color14": "#413535",
    "color15": "#1b1b1b"
  }
}